asposecells/__init__.py
asposecells/api.py
asposecells/api.pyi
asposecells/lib/JavaClassBridge.jar
asposecells/lib/aspose-cells-26.1.jar
asposecells/lib/bcpkix-jdk15on-1.68.jar
asposecells/lib/bcprov-jdk15on-1.68.jar
aspose_cells-26.1.0.dist-info/METADATA
aspose_cells-26.1.0.dist-info/WHEEL
aspose_cells-26.1.0.dist-info/top_level.txt
aspose_cells-26.1.0.dist-info/RECORD
