Metadata-Version: 2.1
Name: aspose-cells
Version: 26.1.0
Summary: Aspose.Cells for Python via Java is a high-performance library that unleashes the full potential of Excel in your Python projects. It can be used to efficiently manipulate and convert Excel and spreadsheet formats including XLS, XLSX, XLSB, ODS, CSV, and HTML - all from your Python code. Amazingly, it also offers free support.
Home-page: https://products.aspose.com/cells/python-java
Author: Aspose
Author-email: cells@aspose.com
License: UNKNOWN
Keywords: Excel,XLS,XLSX,XLSB,CSV,to,PDF,JPG,PNG,HTML,ODS,Numbers,XLSM,OOXML,Spreadsheet,Markdown,XPS,DOCX,PPTX,MHTML,SVG,JSON,XML,SQL
Platform: Operating System :: MacOS :: MacOS X
Platform: Operating System :: Microsoft :: Windows :: Windows 7
Platform: Operating System :: Microsoft :: Windows :: Windows Vista
Platform: Operating System :: POSIX :: Linux
Classifier: Programming Language :: Python :: 3.8
Classifier: License :: Other/Proprietary License
Requires-Python: <=3.13, >=3.8
Requires-Dist: JPype1>=1.2.1
